urcous/__init__.py
urcous/_2d/__init__.py
urcous/_2d/renderer.py
urcous/_2d/scene.py
urcous/_2d/shapes.py
urcous/_2d/transform.py
urcous/_2d/vector2d.py
urcous/_3d/__init__.py
urcous/_3d/application.py
urcous/_3d/camera.py
urcous/_3d/matrix.py
urcous/_3d/mesh.py
urcous/_3d/renderer.py
urcous/_3d/vector3d.py
Urcous-0.5.dist-info/METADATA
Urcous-0.5.dist-info/WHEEL
Urcous-0.5.dist-info/top_level.txt
Urcous-0.5.dist-info/RECORD
